{
  "date": "2024-07-02",
  "time": "23:59",
  "year_round": {
    "Красота": {
      "total_orders": 106,
      "total_revenue": 76962.71,
      "delivery_orders": 0,
      "delivery_revenue": 0.0,
      "pickup_orders": 0,
      "pickup_revenue": 0.0,
      "cafe_orders": 106,
      "cafe_revenue": 76962.71
    },
    "Луговая": {
      "total_orders": 114,
      "total_revenue": 63229.39000000001,
      "delivery_orders": 0,
      "delivery_revenue": 0.0,
      "pickup_orders": 0,
      "pickup_revenue": 0.0,
      "cafe_orders": 114,
      "cafe_revenue": 63229.39000000001
    },
    "Парк": {
      "total_orders": 0,
      "total_revenue": 0.0,
      "delivery_orders": 0,
      "delivery_revenue": 0.0,
      "pickup_orders": 0,
      "pickup_revenue": 0.0,
      "cafe_orders": 0,
      "cafe_revenue": 0.0
    },
    "Светланская": {
      "total_orders": 157,
      "total_revenue": 78701.73999999999,
      "delivery_orders": 0,
      "delivery_revenue": 0.0,
      "pickup_orders": 0,
      "pickup_revenue": 0.0,
      "cafe_orders": 157,
      "cafe_revenue": 78701.73999999999
    },
    "Чуркин": {
      "total_orders": 182,
      "total_revenue": 88476.43999999999,
      "delivery_orders": 0,
      "delivery_revenue": 0.0,
      "pickup_orders": 0,
      "pickup_revenue": 0.0,
      "cafe_orders": 182,
      "cafe_revenue": 88476.43999999999
    },
    "Тихая": {
      "total_orders": 0,
      "total_revenue": 0.0,
      "delivery_orders": 0,
      "delivery_revenue": 0.0,
      "pickup_orders": 0,
      "pickup_revenue": 0.0,
      "cafe_orders": 0,
      "cafe_revenue": 0.0
    },
    "Тобольская": {
      "total_orders": 94,
      "total_revenue": 49994.02,
      "delivery_orders": 0,
      "delivery_revenue": 0.0,
      "pickup_orders": 0,
      "pickup_revenue": 0.0,
      "cafe_orders": 94,
      "cafe_revenue": 49994.02
    }
  },
  "seasonal": {
    "Юбилейный": {
      "total_orders": 0,
      "total_revenue": 0.0,
      "delivery_orders": 0,
      "delivery_revenue": 0.0,
      "pickup_orders": 0,
      "pickup_revenue": 0.0,
      "cafe_orders": 0,
      "cafe_revenue": 0.0
    },
    "Кунгас": {
      "total_orders": 0,
      "total_revenue": 0.0,
      "delivery_orders": 0,
      "delivery_revenue": 0.0,
      "pickup_orders": 0,
      "pickup_revenue": 0.0,
      "cafe_orders": 0,
      "cafe_revenue": 0.0
    },
    "МГУ": {
      "total_orders": 216,
      "total_revenue": 95656.4,
      "delivery_orders": 0,
      "delivery_revenue": 0.0,
      "pickup_orders": 0,
      "pickup_revenue": 0.0,
      "cafe_orders": 216,
      "cafe_revenue": 95656.4
    },
    "Патрокл": {
      "total_orders": 0,
      "total_revenue": 0.0,
      "delivery_orders": 0,
      "delivery_revenue": 0.0,
      "pickup_orders": 0,
      "pickup_revenue": 0.0,
      "cafe_orders": 0,
      "cafe_revenue": 0.0
    }
  },
  "total": {
    "total_orders": 869,
    "total_revenue": 453020.69999999995,
    "total_delivery_orders": 0,
    "total_delivery_revenue": 0.0,
    "total_pickup_orders": 0,
    "total_pickup_revenue": 0.0,
    "total_cafe_orders": 869,
    "total_cafe_revenue": 453020.69999999995
  },
  "plan": {
    "revenue": 14324598.25577,
    "orders": 23644.269
  },
  "sales": {
    "Светланская": {
      "Лапша": 83,
      "Рис": 41,
      "Курица": 58,
      "Свинина": 17,
      "Креветка": 43,
      "Бекон": 24,
      "Соломка": 5.6,
      "Кубик": 3.3,
      "Салаты - Супы": {
        "Азиатский салат с курицей": 7,
        "Азиатский салат с креветкой": 1,
        "Тайский суп": 6,
        "Вьетнамский суп": 0
      },
      "Пельмени - Бао-банс": {
        "Пельмени с курицей": 7,
        "Бао-банс с курицей": 0
      }
    },
    "Луговая": {
      "Лапша": 61,
      "Рис": 19,
      "Курица": 29,
      "Свинина": 22,
      "Креветка": 19,
      "Бекон": 18,
      "Соломка": 4.4,
      "Кубик": 1.32,
      "Салаты - Супы": {
        "Азиатский салат с курицей": 7,
        "Азиатский салат с креветкой": 0,
        "Тайский суп": 7,
        "Вьетнамский суп": 0
      },
      "Пельмени - Бао-банс": {
        "Пельмени с курицей": 0,
        "Бао-банс с курицей": 0
      }
    },
    "МГУ": {
      "Лапша": 147,
      "Рис": 60,
      "Курица": 112,
      "Свинина": 43,
      "Креветка": 45,
      "Бекон": 18,
      "Соломка": 14.7,
      "Кубик": 4.62,
      "Салаты - Супы": {
        "Азиатский салат с курицей": 4,
        "Азиатский салат с креветкой": 8,
        "Тайский суп": 7,
        "Вьетнамский суп": 0
      },
      "Пельмени - Бао-банс": {
        "Пельмени с курицей": 0,
        "Бао-банс с курицей": 0
      }
    },
    "Красота": {
      "Лапша": 63,
      "Рис": 38,
      "Курица": 40,
      "Свинина": 23,
      "Креветка": 25,
      "Бекон": 24,
      "Соломка": 4.2,
      "Кубик": 3.08,
      "Салаты - Супы": {
        "Азиатский салат с курицей": 7,
        "Азиатский салат с креветкой": 3,
        "Тайский суп": 11,
        "Вьетнамский суп": 0
      },
      "Пельмени - Бао-банс": {
        "Пельмени с курицей": 0,
        "Бао-банс с курицей": 0
      }
    },
    "Тобольская": {
      "Лапша": 48,
      "Рис": 28,
      "Курица": 31,
      "Свинина": 5,
      "Креветка": 27,
      "Бекон": 22,
      "Соломка": 2.6,
      "Кубик": 2.2,
      "Салаты - Супы": {
        "Азиатский салат с курицей": 4,
        "Азиатский салат с креветкой": 3,
        "Тайский суп": 3,
        "Вьетнамский суп": 0
      },
      "Пельмени - Бао-банс": {
        "Пельмени с курицей": 0,
        "Бао-банс с курицей": 0
      }
    },
    "Фонтантая ": {
      "Лапша": 44,
      "Рис": 19,
      "Курица": 47,
      "Свинина": 0,
      "Креветка": 13,
      "Бекон": 2,
      "Соломка": 4.3999999999999995,
      "Кубик": 1.87,
      "Салаты - Супы": {
        "Азиатский салат с курицей": 3,
        "Азиатский салат с креветкой": 0,
        "Тайский суп": 0,
        "Вьетнамский суп": 0
      },
      "Пельмени - Бао-банс": {
        "Пельмени с курицей": 0,
        "Бао-банс с курицей": 0
      }
    },
    "Чуркин": {
      "Лапша": 143,
      "Рис": 47,
      "Курица": 62,
      "Свинина": 38,
      "Креветка": 57,
      "Бекон": 38,
      "Соломка": 9.3,
      "Кубик": 3.63,
      "Салаты - Супы": {
        "Азиатский салат с курицей": 3,
        "Азиатский салат с креветкой": 2,
        "Тайский суп": 6,
        "Вьетнамский суп": 0
      },
      "Пельмени - Бао-банс": {
        "Пельмени с курицей": 2,
        "Бао-банс с курицей": 0
      }
    },
    "татарка": {
      "Лапша": 218,
      "Рис": 77,
      "Курица": 187,
      "Свинина": 48,
      "Креветка": 55,
      "Бекон": 9,
      "Соломка": 21.8,
      "Кубик": 7.37,
      "Салаты - Супы": {
        "Азиатский салат с курицей": 8,
        "Азиатский салат с креветкой": 7,
        "Тайский суп": 6,
        "Вьетнамский суп": 0
      },
      "Пельмени - Бао-банс": {
        "Пельмени с курицей": 0,
        "Бао-банс с курицей": 0
      }
    },
    "Парк": {
      "Лапша": 0,
      "Рис": 0,
      "Курица": 0,
      "Свинина": 0,
      "Креветка": 0,
      "Бекон": 0,
      "Соломка": 0.0,
      "Кубик": 0.0,
      "Салаты - Супы": {
        "Азиатский салат с курицей": 0,
        "Азиатский салат с креветкой": 0,
        "Тайский суп": 0,
        "Вьетнамский суп": 0
      },
      "Пельмени - Бао-банс": {
        "Пельмени с курицей": 0,
        "Бао-банс с курицей": 0
      }
    },
    "Тихая": {
      "Лапша": 0,
      "Рис": 0,
      "Курица": 0,
      "Свинина": 0,
      "Креветка": 0,
      "Бекон": 0,
      "Соломка": 0.0,
      "Кубик": 0.0,
      "Салаты - Супы": {
        "Азиатский салат с курицей": 0,
        "Азиатский салат с креветкой": 0,
        "Тайский суп": 0,
        "Вьетнамский суп": 0
      },
      "Пельмени - Бао-банс": {
        "Пельмени с курицей": 0,
        "Бао-банс с курицей": 0
      }
    },
    "Юбилейный": {
      "Лапша": 0,
      "Рис": 0,
      "Курица": 0,
      "Свинина": 0,
      "Креветка": 0,
      "Бекон": 0,
      "Соломка": 0.0,
      "Кубик": 0.0,
      "Салаты - Супы": {
        "Азиатский салат с курицей": 0,
        "Азиатский салат с креветкой": 0,
        "Тайский суп": 0,
        "Вьетнамский суп": 0
      },
      "Пельмени - Бао-банс": {
        "Пельмени с курицей": 0,
        "Бао-банс с курицей": 0
      }
    },
    "Кунгас": {
      "Лапша": 0,
      "Рис": 0,
      "Курица": 0,
      "Свинина": 0,
      "Креветка": 0,
      "Бекон": 0,
      "Соломка": 0.0,
      "Кубик": 0.0,
      "Салаты - Супы": {
        "Азиатский салат с курицей": 0,
        "Азиатский салат с креветкой": 0,
        "Тайский суп": 0,
        "Вьетнамский суп": 0
      },
      "Пельмени - Бао-банс": {
        "Пельмени с курицей": 0,
        "Бао-банс с курицей": 0
      }
    },
    "Патрокл": {
      "Лапша": 0,
      "Рис": 0,
      "Курица": 0,
      "Свинина": 0,
      "Креветка": 0,
      "Бекон": 0,
      "Соломка": 0.0,
      "Кубик": 0.0,
      "Салаты - Супы": {
        "Азиатский салат с курицей": 0,
        "Азиатский салат с креветкой": 0,
        "Тайский суп": 0,
        "Вьетнамский суп": 0
      },
      "Пельмени - Бао-банс": {
        "Пельмени с курицей": 0,
        "Бао-банс с курицей": 0
      }
    }
  }
}