{
  "date": "2024-09-09",
  "time": "23:59",
  "year_round": {
    "Красота": {
      "total_orders": 120,
      "total_revenue": 95600.36,
      "delivery_orders": 43,
      "delivery_revenue": 50346.29,
      "pickup_orders": 26,
      "pickup_revenue": 14046.07,
      "cafe_orders": 51,
      "cafe_revenue": 31208.0
    },
    "Луговая": {
      "total_orders": 81,
      "total_revenue": 48966.08,
      "delivery_orders": 14,
      "delivery_revenue": 13137.789999999999,
      "pickup_orders": 15,
      "pickup_revenue": 10900.7,
      "cafe_orders": 52,
      "cafe_revenue": 24927.59
    },
    "Парк": {
      "total_orders": 0,
      "total_revenue": 0.0,
      "delivery_orders": 0,
      "delivery_revenue": 0.0,
      "pickup_orders": 0,
      "pickup_revenue": 0.0,
      "cafe_orders": 0,
      "cafe_revenue": 0.0
    },
    "Светланская": {
      "total_orders": 110,
      "total_revenue": 66563.91,
      "delivery_orders": 14,
      "delivery_revenue": 17436.59,
      "pickup_orders": 19,
      "pickup_revenue": 8735.32,
      "cafe_orders": 77,
      "cafe_revenue": 40392.0
    },
    "Чуркин": {
      "total_orders": 154,
      "total_revenue": 78105.73,
      "delivery_orders": 5,
      "delivery_revenue": 6275.280000000001,
      "pickup_orders": 23,
      "pickup_revenue": 9512.06,
      "cafe_orders": 126,
      "cafe_revenue": 62318.39
    },
    "Тихая": {
      "total_orders": 148,
      "total_revenue": 85015.44000000002,
      "delivery_orders": 4,
      "delivery_revenue": 5846.0,
      "pickup_orders": 23,
      "pickup_revenue": 12153.34,
      "cafe_orders": 121,
      "cafe_revenue": 67016.1
    },
    "Тобольская": {
      "total_orders": 90,
      "total_revenue": 59759.869999999995,
      "delivery_orders": 20,
      "delivery_revenue": 21858.620000000003,
      "pickup_orders": 19,
      "pickup_revenue": 10229.07,
      "cafe_orders": 51,
      "cafe_revenue": 27672.18
    }
  },
  "seasonal": {
    "Юбилейный": {
      "total_orders": 0,
      "total_revenue": 0.0,
      "delivery_orders": 0,
      "delivery_revenue": 0.0,
      "pickup_orders": 0,
      "pickup_revenue": 0.0,
      "cafe_orders": 0,
      "cafe_revenue": 0.0
    },
    "Кунгас": {
      "total_orders": 0,
      "total_revenue": 0.0,
      "delivery_orders": 0,
      "delivery_revenue": 0.0,
      "pickup_orders": 0,
      "pickup_revenue": 0.0,
      "cafe_orders": 0,
      "cafe_revenue": 0.0
    },
    "МГУ": {
      "total_orders": 120,
      "total_revenue": 46557.0,
      "delivery_orders": 0,
      "delivery_revenue": 0.0,
      "pickup_orders": 4,
      "pickup_revenue": 3372.0,
      "cafe_orders": 116,
      "cafe_revenue": 43185.0
    },
    "Патрокл": {
      "total_orders": 0,
      "total_revenue": 0.0,
      "delivery_orders": 0,
      "delivery_revenue": 0.0,
      "pickup_orders": 0,
      "pickup_revenue": 0.0,
      "cafe_orders": 0,
      "cafe_revenue": 0.0
    }
  },
  "total": {
    "total_orders": 823,
    "total_revenue": 480568.39,
    "total_delivery_orders": 100,
    "total_delivery_revenue": 114900.57,
    "total_pickup_orders": 129,
    "total_pickup_revenue": 68948.56,
    "total_cafe_orders": 594,
    "total_cafe_revenue": 296719.26
  },
  "plan": {
    "revenue": 15529666.19732,
    "orders": 24499.502
  },
  "sales": {
    "Светланская": {
      "Лапша": 80,
      "Рис": 34,
      "Курица": 36,
      "Свинина": 18,
      "Креветка": 49,
      "Бекон": 24,
      "Соломка": 4.9,
      "Кубик": 2.75,
      "Салаты - Супы": {
        "Азиатский салат с курицей": 3,
        "Азиатский салат с креветкой": 1,
        "Тайский суп с курицей": 4,
        "Тайский суп с креветкой": 6,
        "Вьетнамский суп": 1
      },
      "Пельмени - Бао-банс": {
        "Пельмени с курицей": 5,
        "Бао-банс с курицей": 0
      }
    },
    "Луговая": {
      "Лапша": 65,
      "Рис": 19,
      "Курица": 35,
      "Свинина": 16,
      "Креветка": 32,
      "Бекон": 15,
      "Соломка": 4.4,
      "Кубик": 1.4300000000000002,
      "Салаты - Супы": {
        "Азиатский салат с курицей": 4,
        "Азиатский салат с креветкой": 0,
        "Тайский суп с курицей": 2,
        "Тайский суп с креветкой": 6,
        "Вьетнамский суп": 10
      },
      "Пельмени - Бао-банс": {
        "Пельмени с курицей": 0,
        "Бао-банс с курицей": 0
      }
    },
    "МГУ": {
      "Лапша": 52,
      "Рис": 31,
      "Курица": 28,
      "Свинина": 16,
      "Креветка": 25,
      "Бекон": 9,
      "Соломка": 5.2,
      "Кубик": 2.42,
      "Салаты - Супы": {
        "Азиатский салат с курицей": 5,
        "Азиатский салат с креветкой": 1,
        "Тайский суп с курицей": 2,
        "Тайский суп с креветкой": 0,
        "Вьетнамский суп": 0
      },
      "Пельмени - Бао-банс": {
        "Пельмени с курицей": 0,
        "Бао-банс с курицей": 0
      }
    },
    "Красота": {
      "Лапша": 85,
      "Рис": 47,
      "Курица": 48,
      "Свинина": 15,
      "Креветка": 52,
      "Бекон": 39,
      "Соломка": 4.4,
      "Кубик": 3.63,
      "Салаты - Супы": {
        "Азиатский салат с курицей": 10,
        "Азиатский салат с креветкой": 4,
        "Тайский суп с курицей": 6,
        "Тайский суп с креветкой": 4,
        "Вьетнамский суп": 3
      },
      "Пельмени - Бао-банс": {
        "Пельмени с курицей": 0,
        "Бао-банс с курицей": 0
      }
    },
    "Тобольская": {
      "Лапша": 68,
      "Рис": 24,
      "Курица": 35,
      "Свинина": 17,
      "Креветка": 47,
      "Бекон": 12,
      "Соломка": 4.5,
      "Кубик": 2.42,
      "Салаты - Супы": {
        "Азиатский салат с курицей": 3,
        "Азиатский салат с креветкой": 5,
        "Тайский суп с курицей": 2,
        "Тайский суп с креветкой": 5,
        "Вьетнамский суп": 3
      },
      "Пельмени - Бао-банс": {
        "Пельмени с курицей": 0,
        "Бао-банс с курицей": 0
      }
    },
    "Фонтантая ": {
      "Лапша": 3,
      "Рис": 3,
      "Курица": 1,
      "Свинина": 0,
      "Креветка": 7,
      "Бекон": 0,
      "Соломка": 0.30000000000000004,
      "Кубик": 0.33,
      "Салаты - Супы": {
        "Азиатский салат с курицей": 1,
        "Азиатский салат с креветкой": 1,
        "Тайский суп с курицей": 0,
        "Тайский суп с креветкой": 0,
        "Вьетнамский суп": 0
      },
      "Пельмени - Бао-банс": {
        "Пельмени с курицей": 0,
        "Бао-банс с курицей": 0
      }
    },
    "Тихая": {
      "Лапша": 127,
      "Рис": 48,
      "Курица": 73,
      "Свинина": 25,
      "Креветка": 59,
      "Бекон": 33,
      "Соломка": 8.600000000000001,
      "Кубик": 3.74,
      "Салаты - Супы": {
        "Азиатский салат с курицей": 6,
        "Азиатский салат с креветкой": 0,
        "Тайский суп с курицей": 5,
        "Тайский суп с креветкой": 7,
        "Вьетнамский суп": 4
      },
      "Пельмени - Бао-банс": {
        "Пельмени с курицей": 0,
        "Бао-банс с курицей": 0
      }
    },
    "Чуркин": {
      "Лапша": 113,
      "Рис": 38,
      "Курица": 66,
      "Свинина": 30,
      "Креветка": 48,
      "Бекон": 29,
      "Соломка": 7.8999999999999995,
      "Кубик": 3.41,
      "Салаты - Супы": {
        "Азиатский салат с курицей": 8,
        "Азиатский салат с креветкой": 2,
        "Тайский суп с курицей": 3,
        "Тайский суп с креветкой": 4,
        "Вьетнамский суп": 9
      },
      "Пельмени - Бао-банс": {
        "Пельмени с курицей": 9,
        "Бао-банс с курицей": 0
      }
    },
    "татарка": {
      "Лапша": 94,
      "Рис": 53,
      "Курица": 83,
      "Свинина": 17,
      "Креветка": 46,
      "Бекон": 11,
      "Соломка": 9.4,
      "Кубик": 4.62,
      "Салаты - Супы": {
        "Азиатский салат с курицей": 6,
        "Азиатский салат с креветкой": 3,
        "Тайский суп с курицей": 1,
        "Тайский суп с креветкой": 6,
        "Вьетнамский суп": 0
      },
      "Пельмени - Бао-банс": {
        "Пельмени с курицей": 0,
        "Бао-банс с курицей": 0
      }
    },
    "Парк": {
      "Лапша": 0,
      "Рис": 0,
      "Курица": 0,
      "Свинина": 0,
      "Креветка": 0,
      "Бекон": 0,
      "Соломка": 0.0,
      "Кубик": 0.0,
      "Салаты - Супы": {
        "Азиатский салат с курицей": 0,
        "Азиатский салат с креветкой": 0,
        "Тайский суп с курицей": 0,
        "Тайский суп с креветкой": 0,
        "Вьетнамский суп": 0
      },
      "Пельмени - Бао-банс": {
        "Пельмени с курицей": 0,
        "Бао-банс с курицей": 0
      }
    },
    "Юбилейный": {
      "Лапша": 0,
      "Рис": 0,
      "Курица": 0,
      "Свинина": 0,
      "Креветка": 0,
      "Бекон": 0,
      "Соломка": 0.0,
      "Кубик": 0.0,
      "Салаты - Супы": {
        "Азиатский салат с курицей": 0,
        "Азиатский салат с креветкой": 0,
        "Тайский суп с курицей": 0,
        "Тайский суп с креветкой": 0,
        "Вьетнамский суп": 0
      },
      "Пельмени - Бао-банс": {
        "Пельмени с курицей": 0,
        "Бао-банс с курицей": 0
      }
    },
    "Кунгас": {
      "Лапша": 0,
      "Рис": 0,
      "Курица": 0,
      "Свинина": 0,
      "Креветка": 0,
      "Бекон": 0,
      "Соломка": 0.0,
      "Кубик": 0.0,
      "Салаты - Супы": {
        "Азиатский салат с курицей": 0,
        "Азиатский салат с креветкой": 0,
        "Тайский суп с курицей": 0,
        "Тайский суп с креветкой": 0,
        "Вьетнамский суп": 0
      },
      "Пельмени - Бао-банс": {
        "Пельмени с курицей": 0,
        "Бао-банс с курицей": 0
      }
    },
    "Патрокл": {
      "Лапша": 0,
      "Рис": 0,
      "Курица": 0,
      "Свинина": 0,
      "Креветка": 0,
      "Бекон": 0,
      "Соломка": 0.0,
      "Кубик": 0.0,
      "Салаты - Супы": {
        "Азиатский салат с курицей": 0,
        "Азиатский салат с креветкой": 0,
        "Тайский суп с курицей": 0,
        "Тайский суп с креветкой": 0,
        "Вьетнамский суп": 0
      },
      "Пельмени - Бао-банс": {
        "Пельмени с курицей": 0,
        "Бао-банс с курицей": 0
      }
    }
  }
}