{
  "date": "2025-12-17",
  "time": "19:00",
  "year_round": {
    "Светланская": {
      "total_orders": 40,
      "total_revenue": 30841.0,
      "delivery_orders": 6,
      "delivery_revenue": 8603.0,
      "pickup_orders": 14,
      "pickup_revenue": 9523.0,
      "cafe_orders": 20,
      "cafe_revenue": 12715.0
    },
    "Красота": {
      "total_orders": 65,
      "total_revenue": 67864.0,
      "delivery_orders": 31,
      "delivery_revenue": 44572.0,
      "pickup_orders": 13,
      "pickup_revenue": 9101.0,
      "cafe_orders": 21,
      "cafe_revenue": 14191.0
    },
    "Тобольская": {
      "total_orders": 57,
      "total_revenue": 59322.5,
      "delivery_orders": 20,
      "delivery_revenue": 33265.0,
      "pickup_orders": 5,
      "pickup_revenue": 3769.0,
      "cafe_orders": 32,
      "cafe_revenue": 22288.5
    },
    "Тихая": {
      "total_orders": 45,
      "total_revenue": 29944.0,
      "delivery_orders": 6,
      "delivery_revenue": 9794.0,
      "pickup_orders": 10,
      "pickup_revenue": 6221.0,
      "cafe_orders": 29,
      "cafe_revenue": 13929.0
    },
    "Чуркин": {
      "total_orders": 103,
      "total_revenue": 67480.0,
      "delivery_orders": 5,
      "delivery_revenue": 6720.0,
      "pickup_orders": 15,
      "pickup_revenue": 10918.0,
      "cafe_orders": 83,
      "cafe_revenue": 49842.0
    }
  },
  "seasonal": {},
  "total": {
    "total_orders": 310,
    "total_revenue": 255451.5,
    "total_delivery_orders": 68,
    "total_delivery_revenue": 102954.0,
    "total_pickup_orders": 57,
    "total_pickup_revenue": 39532.0,
    "total_cafe_orders": 185,
    "total_cafe_revenue": 112965.5
  },
  "plan": {
    "revenue": 11100863.3935,
    "orders": 13052.461
  },
  "sales": {
    "Светланская": {
      "Лапша": 23,
      "Стеклянная лапша": 3,
      "Рис": 16,
      "Курица": 17,
      "Свинина": 6,
      "Креветка": 11,
      "Бекон": 7,
      "Соломка": 1.7000000000000002,
      "Кубик": 1.21,
      "Лук": 9,
      "Куриные стрипсы (порции)": 31,
      "Салаты_курица": 4,
      "Салаты_креветка": 0,
      "Харбинский салат": 0,
      "Го Ба Жоу": 0,
      "Супы_тайские_креветка": 0,
      "Супы_тайские_курица": 3,
      "Супы_вьетнамские": 4,
      "Пельмени": 1,
      "Бао-банс": 3,
      "Сырники": 1,
      "Картофель_фри": 0,
      "Соус_Чифань_л": 2.52,
      "Соус_Сливочный_л": 0.45,
      "Соус_Сырный_л": 0.99,
      "Соус_Кимчи_л": 0.36,
      "Соус_Падтай_л": 0.27,
      "Масло_л": 1.56
    },
    "Красота": {
      "Лапша": 44,
      "Стеклянная лапша": 7,
      "Рис": 34,
      "Курица": 40,
      "Свинина": 8,
      "Креветка": 28,
      "Бекон": 21,
      "Соломка": 2.6,
      "Кубик": 3.08,
      "Лук": 21,
      "Куриные стрипсы (порции)": 32,
      "Салаты_курица": 4,
      "Салаты_креветка": 6,
      "Харбинский салат": 0,
      "Го Ба Жоу": 0,
      "Супы_тайские_креветка": 3,
      "Супы_тайские_курица": 1,
      "Супы_вьетнамские": 3,
      "Пельмени": 7,
      "Бао-банс": 4,
      "Сырники": 3,
      "Картофель_фри": 3,
      "Соус_Чифань_л": 4.859999999999999,
      "Соус_Сливочный_л": 1.44,
      "Соус_Сырный_л": 1.8900000000000001,
      "Соус_Кимчи_л": 0.45,
      "Соус_Падтай_л": 0.63,
      "Масло_л": 3.1199999999999997
    },
    "Тобольская": {
      "Лапша": 42,
      "Стеклянная лапша": 6,
      "Рис": 15,
      "Курица": 23,
      "Свинина": 16,
      "Креветка": 27,
      "Бекон": 15,
      "Соломка": 4.0,
      "Кубик": 1.32,
      "Лук": 19,
      "Куриные стрипсы (порции)": 48,
      "Салаты_курица": 2,
      "Салаты_креветка": 2,
      "Харбинский салат": 0,
      "Го Ба Жоу": 0,
      "Супы_тайские_креветка": 4,
      "Супы_тайские_курица": 2,
      "Супы_вьетнамские": 7,
      "Пельмени": 3,
      "Бао-банс": 4,
      "Сырники": 0,
      "Картофель_фри": 3,
      "Соус_Чифань_л": 4.68,
      "Соус_Сливочный_л": 1.44,
      "Соус_Сырный_л": 0.72,
      "Соус_Кимчи_л": 0.27,
      "Соус_Падтай_л": 0.54,
      "Масло_л": 2.5500000000000003
    },
    "Тихая": {
      "Лапша": 21,
      "Стеклянная лапша": 2,
      "Рис": 13,
      "Курица": 20,
      "Свинина": 8,
      "Креветка": 13,
      "Бекон": 8,
      "Соломка": 2.3,
      "Кубик": 0.99,
      "Лук": 10,
      "Куриные стрипсы (порции)": 18,
      "Салаты_курица": 4,
      "Салаты_креветка": 0,
      "Харбинский салат": 0,
      "Го Ба Жоу": 0,
      "Супы_тайские_креветка": 1,
      "Супы_тайские_курица": 2,
      "Супы_вьетнамские": 4,
      "Пельмени": 0,
      "Бао-банс": 6,
      "Сырники": 0,
      "Картофель_фри": 4,
      "Соус_Чифань_л": 2.8800000000000003,
      "Соус_Сливочный_л": 0.72,
      "Соус_Сырный_л": 0.27,
      "Соус_Кимчи_л": 0.18,
      "Соус_Падтай_л": 0.18,
      "Масло_л": 1.4700000000000002
    },
    "Чуркин": {
      "Лапша": 43,
      "Стеклянная лапша": 1,
      "Рис": 31,
      "Курица": 43,
      "Свинина": 12,
      "Креветка": 34,
      "Бекон": 14,
      "Соломка": 4.300000000000001,
      "Кубик": 2.86,
      "Лук": 23,
      "Куриные стрипсы (порции)": 26,
      "Салаты_курица": 3,
      "Салаты_креветка": 4,
      "Харбинский салат": 0,
      "Го Ба Жоу": 0,
      "Супы_тайские_креветка": 0,
      "Супы_тайские_курица": 3,
      "Супы_вьетнамские": 4,
      "Пельмени": 5,
      "Бао-банс": 6,
      "Сырники": 2,
      "Картофель_фри": 9,
      "Соус_Чифань_л": 6.21,
      "Соус_Сливочный_л": 1.71,
      "Соус_Сырный_л": 1.08,
      "Соус_Кимчи_л": 0.36,
      "Соус_Падтай_л": 0.09,
      "Масло_л": 3.1799999999999993
    },
    "Луговая": {
      "Лапша": 0,
      "Стеклянная лапша": 0,
      "Рис": 0,
      "Курица": 0,
      "Свинина": 0,
      "Креветка": 0,
      "Бекон": 0,
      "Соломка": 0.0,
      "Кубик": 0.0,
      "Лук": 0,
      "Куриные стрипсы (порции)": 0,
      "Салаты_курица": 0,
      "Салаты_креветка": 0,
      "Харбинский салат": 0,
      "Го Ба Жоу": 0,
      "Супы_тайские_креветка": 0,
      "Супы_тайские_курица": 0,
      "Супы_вьетнамские": 0,
      "Пельмени": 0,
      "Бао-банс": 0,
      "Сырники": 0,
      "Картофель_фри": 0,
      "Соус_Чифань_л": 0.0,
      "Соус_Сливочный_л": 0.0,
      "Соус_Сырный_л": 0.0,
      "Соус_Кимчи_л": 0.0,
      "Соус_Падтай_л": 0.0,
      "Масло_л": 0.0
    },
    "Парк": {
      "Лапша": 0,
      "Стеклянная лапша": 0,
      "Рис": 0,
      "Курица": 0,
      "Свинина": 0,
      "Креветка": 0,
      "Бекон": 0,
      "Соломка": 0.0,
      "Кубик": 0.0,
      "Лук": 0,
      "Куриные стрипсы (порции)": 0,
      "Салаты_курица": 0,
      "Салаты_креветка": 0,
      "Харбинский салат": 0,
      "Го Ба Жоу": 0,
      "Супы_тайские_креветка": 0,
      "Супы_тайские_курица": 0,
      "Супы_вьетнамские": 0,
      "Пельмени": 0,
      "Бао-банс": 0,
      "Сырники": 0,
      "Картофель_фри": 0,
      "Соус_Чифань_л": 0.0,
      "Соус_Сливочный_л": 0.0,
      "Соус_Сырный_л": 0.0,
      "Соус_Кимчи_л": 0.0,
      "Соус_Падтай_л": 0.0,
      "Масло_л": 0.0
    },
    "Юбилейный": {
      "Лапша": 0,
      "Стеклянная лапша": 0,
      "Рис": 0,
      "Курица": 0,
      "Свинина": 0,
      "Креветка": 0,
      "Бекон": 0,
      "Соломка": 0.0,
      "Кубик": 0.0,
      "Лук": 0,
      "Куриные стрипсы (порции)": 0,
      "Салаты_курица": 0,
      "Салаты_креветка": 0,
      "Харбинский салат": 0,
      "Го Ба Жоу": 0,
      "Супы_тайские_креветка": 0,
      "Супы_тайские_курица": 0,
      "Супы_вьетнамские": 0,
      "Пельмени": 0,
      "Бао-банс": 0,
      "Сырники": 0,
      "Картофель_фри": 0,
      "Соус_Чифань_л": 0.0,
      "Соус_Сливочный_л": 0.0,
      "Соус_Сырный_л": 0.0,
      "Соус_Кимчи_л": 0.0,
      "Соус_Падтай_л": 0.0,
      "Масло_л": 0.0
    },
    "Кунгас": {
      "Лапша": 0,
      "Стеклянная лапша": 0,
      "Рис": 0,
      "Курица": 0,
      "Свинина": 0,
      "Креветка": 0,
      "Бекон": 0,
      "Соломка": 0.0,
      "Кубик": 0.0,
      "Лук": 0,
      "Куриные стрипсы (порции)": 0,
      "Салаты_курица": 0,
      "Салаты_креветка": 0,
      "Харбинский салат": 0,
      "Го Ба Жоу": 0,
      "Супы_тайские_креветка": 0,
      "Супы_тайские_курица": 0,
      "Супы_вьетнамские": 0,
      "Пельмени": 0,
      "Бао-банс": 0,
      "Сырники": 0,
      "Картофель_фри": 0,
      "Соус_Чифань_л": 0.0,
      "Соус_Сливочный_л": 0.0,
      "Соус_Сырный_л": 0.0,
      "Соус_Кимчи_л": 0.0,
      "Соус_Падтай_л": 0.0,
      "Масло_л": 0.0
    },
    "МГУ": {
      "Лапша": 0,
      "Стеклянная лапша": 0,
      "Рис": 0,
      "Курица": 0,
      "Свинина": 0,
      "Креветка": 0,
      "Бекон": 0,
      "Соломка": 0.0,
      "Кубик": 0.0,
      "Лук": 0,
      "Куриные стрипсы (порции)": 0,
      "Салаты_курица": 0,
      "Салаты_креветка": 0,
      "Харбинский салат": 0,
      "Го Ба Жоу": 0,
      "Супы_тайские_креветка": 0,
      "Супы_тайские_курица": 0,
      "Супы_вьетнамские": 0,
      "Пельмени": 0,
      "Бао-банс": 0,
      "Сырники": 0,
      "Картофель_фри": 0,
      "Соус_Чифань_л": 0.0,
      "Соус_Сливочный_л": 0.0,
      "Соус_Сырный_л": 0.0,
      "Соус_Кимчи_л": 0.0,
      "Соус_Падтай_л": 0.0,
      "Масло_л": 0.0
    },
    "Патрокл": {
      "Лапша": 0,
      "Стеклянная лапша": 0,
      "Рис": 0,
      "Курица": 0,
      "Свинина": 0,
      "Креветка": 0,
      "Бекон": 0,
      "Соломка": 0.0,
      "Кубик": 0.0,
      "Лук": 0,
      "Куриные стрипсы (порции)": 0,
      "Салаты_курица": 0,
      "Салаты_креветка": 0,
      "Харбинский салат": 0,
      "Го Ба Жоу": 0,
      "Супы_тайские_креветка": 0,
      "Супы_тайские_курица": 0,
      "Супы_вьетнамские": 0,
      "Пельмени": 0,
      "Бао-банс": 0,
      "Сырники": 0,
      "Картофель_фри": 0,
      "Соус_Чифань_л": 0.0,
      "Соус_Сливочный_л": 0.0,
      "Соус_Сырный_л": 0.0,
      "Соус_Кимчи_л": 0.0,
      "Соус_Падтай_л": 0.0,
      "Масло_л": 0.0
    }
  }
}