{
  "date": "2025-10-08",
  "time": "14:48",
  "year_round": {
    "Парк": {
      "total_orders": 3,
      "delivery_orders": 0,
      "pickup_orders": 2,
      "cafe_orders": 1,
      "total_revenue": 2720.0,
      "delivery_revenue": 0,
      "pickup_revenue": 2028.0,
      "cafe_revenue": 692.0
    },
    "Красота": {
      "total_orders": 31,
      "delivery_orders": 7,
      "pickup_orders": 8,
      "cafe_orders": 16,
      "total_revenue": 23179.0,
      "delivery_revenue": 10999.0,
      "pickup_revenue": 2994.0,
      "cafe_revenue": 9186.0
    },
    "Тобольская": {
      "total_orders": 29,
      "delivery_orders": 4,
      "pickup_orders": 4,
      "cafe_orders": 21,
      "total_revenue": 21793.0,
      "delivery_revenue": 7925.0,
      "pickup_revenue": 3451.0,
      "cafe_revenue": 10417.0
    },
    "Тихая": {
      "total_orders": 21,
      "delivery_orders": 1,
      "pickup_orders": 2,
      "cafe_orders": 18,
      "total_revenue": 11964.0,
      "delivery_revenue": 575.0,
      "pickup_revenue": 1407.0,
      "cafe_revenue": 9982.0
    },
    "Чуркин": {
      "total_orders": 53,
      "delivery_orders": 0,
      "pickup_orders": 8,
      "cafe_orders": 45,
      "total_revenue": 28671.0,
      "delivery_revenue": 0,
      "pickup_revenue": 4616.0,
      "cafe_revenue": 24055.0
    }
  },
  "seasonal": {
    "Кунгас": {
      "total_orders": 19,
      "delivery_orders": 0,
      "pickup_orders": 1,
      "cafe_orders": 18,
      "total_revenue": 9451.0,
      "delivery_revenue": 0,
      "pickup_revenue": 339.0,
      "cafe_revenue": 9112.0
    },
    "МГУ": {
      "total_orders": 8,
      "delivery_orders": 0,
      "pickup_orders": 0,
      "cafe_orders": 8,
      "total_revenue": 3427.0,
      "delivery_revenue": 0,
      "pickup_revenue": 0,
      "cafe_revenue": 3427.0
    },
    "Юбилейный": {
      "total_orders": 24,
      "delivery_orders": 0,
      "pickup_orders": 0,
      "cafe_orders": 24,
      "total_revenue": 9496.0,
      "delivery_revenue": 0,
      "pickup_revenue": 0,
      "cafe_revenue": 9496.0
    }
  },
  "total": {
    "total_orders": 188,
    "total_revenue": 110701.0
  },
  "plan": {
    "total_revenue": 20944728.513,
    "total_orders": 34869.326
  }
}